{
	"caption": {
		"en_US": "Towns of Day and Night",
		"ru_RU": "Города Дней и Ночей"
	},
	"description": {
		"full": {
			"en_US": "readme.md",
			"ru_RU": "readme_ru.md"
		},
		"short": {
			"en_US": "",
			"ru_RU": ""
		}
	},
	"author": "FanOfHeroes, daemon_n",
	"homepage": "https://github.com/FanOfHeroes/Towns-of-Day-and-Night",
	"icon": {
		"file": "ToDaN.png",
		"index": 0
	},
	"mod_version": "0.61",
	"priority": 0,
	"compatibility": {
		"class": "default",
		"entries": {}
	},
	"platform": "era",
	"info_version": "1.0",
	"plugins": {},
	"category": "graphics"
}